setup.py
m3/__init__.py
m3/component.py
m3/component_factory.py
m3/eeprom.py
m3/gui.py
m3/m3rt_toolbox.py
m3/monitor.py
m3/rt_proxy.py
m3/toolbox_core.py
m3/unit_conversion.py
m3/widgets.py
m3core.egg-info/PKG-INFO
m3core.egg-info/SOURCES.txt
m3core.egg-info/dependency_links.txt
m3core.egg-info/top_level.txt
m3rt/__init__.py