Metadata-Version: 1.0
Name: m3core
Version: 1.9.1
Summary: Python bindings for the M3 real time control software
Home-page: http://mekabot.com
Author: Meka Robotics LLC
Author-email: info@mekabot.com
License: GNU-Lesser
Platform: UNKNOWN
